README.txt
setup.py
PyTabular.egg-info/PKG-INFO
PyTabular.egg-info/SOURCES.txt
PyTabular.egg-info/dependency_links.txt
PyTabular.egg-info/requires.txt
PyTabular.egg-info/top_level.txt
bin/PyTabular_tutorial.ipynb
pytabular/__init__.py
pytabular/formatting.py
pytabular/operators.py
pytabular/tables.py