Metadata-Version: 1.0
Name: PyTabular
Version: 0.1.3
Summary: Package for creating LateX tables.
Home-page: http://pypi.python.org/pypi/PyTabular/
Author: Jake C. Torcasso
Author-email: jaketorcasso@gmail.com
License: LICENSE.txt
Platform: UNKNOWN
